csv_to_info_chunks.py
csv_to_info_chunks-1.0.1.dist-info/METADATA
csv_to_info_chunks-1.0.1.dist-info/WHEEL
csv_to_info_chunks-1.0.1.dist-info/entry_points.txt
csv_to_info_chunks-1.0.1.dist-info/top_level.txt
csv_to_info_chunks-1.0.1.dist-info/RECORD
