Metadata-Version: 2.1
Name: csv-to-info-chunks
Version: 1.0.1
